.gitignore
CHANGELOG.md
Dockerfile.file-queue
Dockerfile.openssh
LICENSE
README.md
docker-compose.yaml
flake.lock
flake.nix
pyproject.toml
setup.cfg
.github/workflows/release.yaml
.github/workflows/test.yaml
fs_task_queue/__init__.py
fs_task_queue/__main__.py
fs_task_queue/cli.py
fs_task_queue/core.py
fs_task_queue/utils.py
fs_task_queue.egg-info/PKG-INFO
fs_task_queue.egg-info/SOURCES.txt
fs_task_queue.egg-info/dependency_links.txt
fs_task_queue.egg-info/entry_points.txt
fs_task_queue.egg-info/requires.txt
fs_task_queue.egg-info/top_level.txt
fs_task_queue/plugins/__init__.py
fs_task_queue/plugins/dask.py
fs_task_queue/plugins/filelock.py
fs_task_queue/plugins/ssh.py
tests/__init__.py
tests/test_integration.py
tests/test_unit.py