Metadata-Version: 2.1
Name: fs-task-queue
Version: 0.1.5
Summary: Filesystem based task queue
License: BSD 3-Clause License
Classifier: Programming Language :: Python :: 3
Requires-Python: >=3.7
Provides-Extra: dev
Provides-Extra: extra
License-File: LICENSE
